cyjupyter/__init__.py
cyjupyter/_version.py
cyjupyter/cytoscape.py
cyjupyter/static/extension.js
cyjupyter/static/index.js
cyjupyter/static/index.js.map
cyjupyter-0.2.0.data/data/etc/jupyter/nbconfig/notebook.d/cytoscape-jupyter-widget.json
cyjupyter-0.2.0.data/data/share/jupyter/nbextensions/cytoscape-jupyter-widget/extension.js
cyjupyter-0.2.0.data/data/share/jupyter/nbextensions/cytoscape-jupyter-widget/index.js
cyjupyter-0.2.0.data/data/share/jupyter/nbextensions/cytoscape-jupyter-widget/index.js.map
cyjupyter-0.2.0.dist-info/METADATA
cyjupyter-0.2.0.dist-info/RECORD
cyjupyter-0.2.0.dist-info/WHEEL
cyjupyter-0.2.0.dist-info/top_level.txt
