Metadata-Version: 2.1
Name: cyjupyter
Version: 0.2.0
Summary: Cytoscape.js widget for Jupyter Notebook
Home-page: https://github.com/idekerlab/cytoscape-jupyter-widget
Author: Keiichiro Ono
Author-email: kono@ucsd.edu
License: UNKNOWN
Keywords: ipython,jupyter,widgets,cytoscape,graph,visualization
Platform: UNKNOWN
Classifier: Development Status :: 4 - Beta
Classifier: Framework :: IPython
Classifier: Intended Audience :: Developers
Classifier: Intended Audience :: Science/Research
Classifier: Topic :: Multimedia :: Graphics
Classifier: Programming Language :: Python :: 2
Classifier: Programming Language :: Python :: 2.7
Classifier: Programming Language :: Python :: 3
Classifier: Programming Language :: Python :: 3.3
Classifier: Programming Language :: Python :: 3.4
Classifier: Programming Language :: Python :: 3.5
Classifier: Programming Language :: Python :: 3.6
Requires-Dist: ipywidgets (>=7.0.0)
